Metadata-Version: 1.0
Name: stackqueue
Version: 9.0
Summary: stackqueue
Home-page: UNKNOWN
Author: UNKNOWN
Author-email: alexanderbrehov36@gmail.com
License: UNKNOWN
Platform: UNKNOWN
